MANIFEST.in
README.rst
setup.py
django_oscar_approval.egg-info/PKG-INFO
django_oscar_approval.egg-info/SOURCES.txt
django_oscar_approval.egg-info/dependency_links.txt
django_oscar_approval.egg-info/requires.txt
django_oscar_approval.egg-info/top_level.txt
oscar_approval/__init__.py
oscar_approval/apps/__init__.py
oscar_approval/apps/approval/__init__.py
oscar_approval/apps/approval/abstract_models.py
oscar_approval/apps/approval/app.py
oscar_approval/apps/approval/decorators.py
oscar_approval/apps/approval/forms.py
oscar_approval/apps/approval/models.py
oscar_approval/apps/approval/receivers.py
oscar_approval/apps/approval/signals.py
oscar_approval/apps/approval/views.py
oscar_approval/apps/catalogue/__init__.py
oscar_approval/apps/catalogue/abstract_models.py
oscar_approval/apps/customer/__init__.py
oscar_approval/apps/customer/abstract_models.py
oscar_approval/apps/customer/views.py
oscar_approval/apps/dashboard/__init__.py
oscar_approval/apps/dashboard/app.py
oscar_approval/apps/dashboard/views.py
oscar_approval/apps/order/__init__.py
oscar_approval/apps/order/receivers.py
oscar_approval/apps/order/utils.py
oscar_approval/templates/oscar_approval/order_line_approval_list.html
oscar_approval/templates/oscar_approval/order_line_approval_tab.html
oscar_approval/templates/oscar_approval/dashboard/approver_management.html
oscar_approval/templates/oscar_approval/dashboard/event_log_list.html