Metadata-Version: 1.1
Name: django-oscar-approval
Version: 0.1
Summary: Order approval module for django-oscar
Home-page: https://github.com/tangentlabs/django-oscar-approval
Author: Tangentlabs
Author-email: tangentlabs@tangentlabs.co.uk
License: BSD
Keywords: order approval,order authorisation
Platform: UNKNOWN
Classifier: Environment :: Web Environment
Classifier: Framework :: Django
Classifier: Intended Audience :: Developers
Classifier: License :: OSI Approved :: BSD License
Classifier: Operating System :: Unix
Classifier: Programming Language :: Python
